<ndef n="001" star="1"/>「含」，聖本作「鋡」。 
<ndef n="002"/>聖本無「東晉罽賓三藏瞿曇僧伽提婆譯」十三字。 
<ndef n="003"/>麗本無「中阿含」三字，今依循每經慣例補上。 
<ndef n="004" star="1"/>「後大品」，麗本作「大品」，今參考卷五十第一七一三頁注(1)改作「後大品」。 
<ndef n="005"/>本經敍說阿梨吒比丘起「行欲者無障礙」之邪見，而自稱是世尊所說，諸比丘訶之，並說世尊言：欲如骨鏁、肉臠、把炬、火坑、毒蛇、夢、假借、樹果等，謂欲有障礙也。世尊又以蛇喻法、筏喻法，諭其當捨顛倒之見，更依次解說(一)六見處，(二)因內有恐怖、因外有恐怖、因內無恐怖、因外無恐怖，(三)於六見處斷神見。中部(M. 22. Alagaddūpamasuttaṃ 蛇喻經)、增一阿含馬血天子品第五經(大二‧七五九下)。 
<ndef n="006" star="1"/>明本無「第五後誦」四字。 
<ndef n="007"/>阿梨吒(Arittha)(巴)，比丘名。 
<ndef n="008" star="1"/>「本伽陀婆利」，巴利本作 Gaddhabādhi pubba(本為馴鷲者)。「利」，麗本作「棃，今依據宋、元、明三本與聖本改作「利」。 
<ndef n="009" star="1"/>「座」，麗本作「坐」，今依據宋、元、明三本改作「座」。 
<ndef n="010"/>「口」，明本作「曰」。 
<ndef n="011"/>「法」，宋、元、明三本與聖本均作「是」。 
<ndef n="012"/>「假借」，巴利本作 yācitaka(借用物)。 
<ndef n="013" star="1"/>「果」，聖本作「菓」。 
<ndef n="014"/>除上述外，巴利本另舉出屠殺場(asisūnā)與鐵刺(sattisūla)兩項，其餘諸譬喻與順序均與漢譯本同。 
<ndef n="015" star="1"/>「耶」，麗本作「也」，今依據宋、元、明三本與聖本改作「耶」。 
<ndef n="016" star="1"/>「責」，聖本作「嘖」。 
<ndef n="017"/>「數」，聖本作「[口*數]」。 
<ndef n="018" star="1"/>「肢」，麗本作「支」，今依據宋、元、明三本與聖本改作「肢」。 
<ndef n="019"/>「疲勞」，宋、元二本均作「勞疲」。 
<ndef n="020"/>「押」，元、明二本均作「壓」。 
<ndef n="021"/>「項」，麗本作「頂」。今依據宋、元、明三本改作「項」。聖本作「頭」。 
<ndef n="022"/>「反」，聖本作「及」。 
<ndef n="023"/>「義」，聖本作「善義」二字。 
<ndef n="024" star="1"/>「船」，麗本作「舡」，今依據宋、元、明三本與聖本改作「船」。 
<ndef n="025" star="1"/>「椑」，宋、元、明三本均作「簿」，聖本作「裨」。 
<ndef n="026"/>「彼便」，宋、元、明三本均作「卽於」。 
<ndef n="027"/>「竟」，宋、元、明三本均作「意」。 
<ndef n="028"/>「彼一切非我有，我非彼有，亦非是神」，巴利本作 N'etaṃ mama, n'eso 'ham asmi, na m'eso attā 其意為：此非我所，此非是我，此非我之(神)我。 
<ndef n="029" star="1"/>「磨」，宋、元、明三本與聖本均作「摩」。 
<ndef n="030"/>「頗有因內有恐怖耶？」巴利本作 siyā nu kho……ajjhattaṃ asati paritassanā 其意為：於內中無「實有」，究竟有恐怖否？ 
<ndef n="031" star="1"/>「椎」，宋、元、明三本均作「槌」，聖本作「推」。 
<ndef n="032"/>「比丘者，如是見……內有恐怖也」，巴利本(M. vol. 1, p.136)作：比丘！此有一類比丘有如此見：彼即是世界，彼即是神我，彼死後〔希望〕我將成為常住、堅固、恆久、非變異法，我將永久如此存在。彼聞如來或如來之弟子，為了斷除一切見處、偏見、纏、執著、隨眠，為了靜止一切行，為了捨棄一切依，為了滅愛，為了離貪，為了滅盡，為了涅槃而說的法。他起如是念：確實，我將被破滅，我實將滅亡，我實將不存在。於是，他憂、惱、悲，搥胸而泣，生起迷妄。比丘！如此是於內中無「實有」而有恐怖。 
<ndef n="033"/>「頗有因內無恐怖耶？」巴利本作 siyā…ajjhattaṃ asati aparitassanā(於內中無「實有」，而無恐怖否？) 
<ndef n="034"/>「也」，宋、元、明三本與聖本均作「耶」。 
<ndef n="035"/>「因外有恐怖耶？」巴利本作 siyā……bahiddhā asati paritassanā 其意為：於外部無「實有」而有恐怖否？ 
<ndef n="036" star="1"/>「來」，聖本作「是」。 
<ndef n="037"/>「啼」，聖本作「勞」。 
<ndef n="038"/>「頗有因外無恐怖耶？」巴利本作 siyā……bahiddhā asati aparitassanā 其意為：於外部無「實有」而無恐怖否？ 
<ndef n="039"/>「受」，聖本作「愛」。 
<ndef n="040"/>宋、元、明三本與聖本均無「受」字。 
<ndef n="041"/>「受」，宋、元、明三本均作「愛」。 
<ndef n="042"/>「則」，麗本作「見」，今依據宋、元、明三本與聖本改作「則」。 
<ndef n="043"/>「所」，麗本作「行」，今依據宋、元、明三本與聖本改作「所」。 
<ndef n="044"/>「我」，麗本作「彼」，今依據宋、元、明三本與聖本改作「我」。 
<ndef n="045"/>「若」，麗本作「所」，今依據宋、元、明三本與聖本改作「若」。 
<ndef n="046"/>「更受」，宋、元、明三本與聖本均作「受後」。 
<ndef n="047" star="1"/>「墎」，元、明二本均作「郭」。 
<ndef n="048" star="1"/>「打」，聖本作「頂」。 
<ndef n="049"/>因提羅(Indra)(梵)、(Inda)(巴)，即帝釋天。 
<ndef n="050"/>伊沙那(Isānā)(巴)，天王名。 
<ndef n="051"/>「如來是梵……如來是不異」，巴利本作 Ditthe……bhikkhave dhamme tathāgataṃ ananuvejjo(於現法不能了知如來)。 
<ndef n="052"/>宋、元、明三本與聖本均無「如來」二字。 
<ndef n="053" star="1"/>「責數」，聖本作「嘖[口*數]」。 
<ndef n="054"/>「今」，聖本作「令」。 
<ndef n="055"/>「我」字之上，麗本有一「有」字，今依據宋、元、明三本與聖本刪去。 
<ndef n="056"/>宋、元、明三本與聖本均無「慧」字。 
<ndef n="057"/>「得」，宋、元、明三本均作「是」。 
<ndef n="058"/>「皆」，宋、元、明三本均作「必」。 
<ndef n="059"/>明本無「阿梨吒經第九竟」七字。 
<ndef n="060"/>宋、元、明三本與聖本均無「四千五百七十字」七字。 
<ndef n="061"/>明本無「中阿含」三字。 
<ndef n="062" star="1"/>「嗏」，麗本作「[口*荼]」，今依據宋、元、明三本均作「嗏」。 
<ndef n="063"/>本經敍說嗏帝比丘起「識」輪迴往生不更異之邪見，世尊教以：(一)緣六根六境生識之緣起法。(二)以栰為喻，諭其雖是如來真說，若是執著則非。(三)四食之緣起及滅，以明所謂十二因緣法，以此為正見。中部(M. 38. Mahātanhāsavkhayasuttaṃ 愛盡大經)。 
<ndef n="064"/>嗏帝(Sāti)(巴)，比丘名。 
<ndef n="065" star="1"/>「雞和哆子」，巴利本作 Kevattaputta(漁夫之子)。「哆」，宋、元、明三本均作「多」。 
<ndef n="066"/>「今此識，往生不更異」，巴利本作 idaṃ viññānaṃ sandhāvati saṃsarati, anaññan 其意為：此識流轉輪迴，〔而且常時保持自己〕同 一性。 
<ndef n="067"/>「起」，宋、元、明三本與聖本均作「起識」二字。 
<ndef n="068"/>「生」字之下，宋本有一「來」字。 
<ndef n="069"/>「耶」，麗本作「也」，今依據磧砂藏改作「耶」。 
<ndef n="070"/>宋、元、明三本與聖本均無「也」字。 
<ndef n="071"/>麗本無「彼」字，今依據宋、元、明三本與聖本補上。 
<ndef n="072"/>「此識說、覺、作、教作、起、等起，謂彼彼作善惡業而受報也」，巴利本作 yvāyaṃ……vado vedeyyo tatra tatra kalyānapāpākānaj kammānaṃ vipākaṃ patisaṃvedeti(此說話者與了解者於此處、彼處受善惡業之果報。) 
<ndef n="073"/>「訶」，大正本作「呵」。 
<ndef n="074"/>「口」，明本作「曰」。 
<ndef n="075"/>「汝」，聖本作「汝法」二字。 
<ndef n="076"/>「意」，聖本作「緣意」二字。 
<ndef n="077"/>「意」，麗本作「緣意」二字，今依據宋、元、明三本刪去。 
<ndef n="078"/>「真說見耶？」，巴利本作 Bhūtaṃ idaṃ ti bhikkhave passatha 其意為：諸比丘！見此是已生者〔否〕？ 
<ndef n="079"/>「如來真說見耶？」巴利本作 Tad-āhārasambhavan ti bhikkhave passatha 其意為：諸比丘！見彼由食所生〔否〕？「食」與「如來」意義相差甚鉅，此或漢譯本將 āhāra 誤作 arahā 所致。 
<ndef n="080" star="1"/>「真」，宋、元、明三本均作「真說」二字。 
<ndef n="081"/>「如來滅已，所有真彼亦滅法見耶？」巴利本作 Tad āhāranirodhā yaṃ bhūtaṃ taṃ nirodhadhammaṃ ti bhikkhave passatha 其意為：諸比丘！見彼凡是已生者，由於食物之滅止，彼亦〔成〕滅止法耶？ 
<ndef n="082"/>「真說無有疑惑耶？」巴利本作 bhūtaṃ idaṃ no-ssūti bhikkhave kavkhāto uppajjati vicikicchā 其意為：諸比丘！由於「此非已生者否 」之猶豫，而產生疑惑。 
<ndef n="083"/>「摶」，聖本作「揣」。 
<ndef n="084"/>「習」，巴利本作 samudaya(集)。 
<ndef n="085"/>「覺」，巴利本作 vedanā(受)。 
<ndef n="086"/>「更樂」，巴利本作 phassa(觸)。 
<ndef n="087"/>「受」，巴利本作 upādāna(取)。 
<ndef n="088"/>「淳」，麗本作「等」，今依據宋、元、明三本與聖本改作「淳」。「淳」通「純」。 
<ndef n="089"/>「也」，麗本作「耶」，今依據宋、元、明三本與聖本改作「也」。 
<ndef n="090"/>「愛」，聖本作「受」。 
<ndef n="091"/>「受」，聖本作「愛」。 
<ndef n="092"/>「滅」字之下，麗本有一「也」字，今依據宋、元、明三本與聖本刪去。 
<ndef n="093"/>「者」、大正本作「然」。 
<ndef n="094"/>「此」字之下，聖本有一「得」字。 
<ndef n="095"/>「弟子」二字，聖本作「佛弟子」三字。 
<ndef n="096"/>「訶」，明本作「漢」。 
<ndef n="097"/>以上之「殺父、殺母、殺阿羅漢、破和合僧、出佛身血」五項惡行稱為「五逆罪」，又作「五無間業」。 
<ndef n="098"/>「作」，明本與聖本均作「仰」。 
<ndef n="099"/>「汝等頗吉祥為清淨耶？」巴利本作 yāni tāni puthusamanabrāhmanānaṃ vatakotūhala-mavgalāni tāni sārato paccāgaccheyyātha(你們以為凡是凡愚的沙門、婆羅門之行儀、祭典、祝典都是真，而想回復嗎？) 
<ndef n="100"/>「毒」，麗本作「之」，今依據聖本改作「毒」。 
<ndef n="101"/>八有(atthama-bhava)(巴)，僅七次往返人天，而不再第八次受生，稱「不受八有」，故「八有」即指「第八次受生」。 
<ndef n="102"/>「香」，宋、元、明三本均作「生」。 
<ndef n="103"/>「持」，宋、元、明三本均作「時」。 
<ndef n="104"/>「便」，大正本作「更」。 
<ndef n="105"/>「酥」，麗本作「蘇」，今依據宋、元、明三本改作「酥」。 
<ndef n="106"/>聖本無「惡」字。 
<ndef n="107"/>「隨」，聖本作「墮」。 
<ndef n="108"/>明本無「嗏帝經第十竟」六字。 
<ndef n="109"/>宋、元、明三本與聖本均無「四千六百九十一字」八字。 
<ndef n="110"/>宋、元、明三本與聖本均卷末題、品末題位置前後。 
<ndef n="111"/>「二」，大正本作「三」。 
<ndef n="112"/>宋、元、明三本與聖本均無「九千二百六十一字」八字。 
<ndef n="113"/>「中阿含後大品第二竟」九字，明本作「後大品第十六竟」七字。 
<ndef n="114"/>宋、元、明三本均無「三萬九千九百一十二字。」十字。 
<ndef n="115"/>明本無「第五後誦」四字，元本作「第三後誦」。「誦」字之下，聖本有「光明皇后願文」六字。